ucp9/__init__.py
ucp9/conversion.py
ucp9/cp932.conf
ucp9/environment.py
ucp9/main.py
ucp9-1.0.1.dist-info/METADATA
ucp9-1.0.1.dist-info/WHEEL
ucp9-1.0.1.dist-info/top_level.txt
ucp9-1.0.1.dist-info/RECORD
