Metadata-Version: 2.1
Name: ucp9
Version: 1.0.1
Summary: Unicode To CP932 Transcoder
Home-page: https://github.com/nhantranz/ucp9
Author: Tran Anh Nhan
Author-email: vfa.nhanta@gmail.com
License: UNKNOWN
Platform: UNKNOWN
Classifier: Programming Language :: Python :: 3
Classifier: License :: OSI Approved :: MIT License
Classifier: Operating System :: OS Independent
